stm32tool/__init__.py
stm32tool/isp.py
stm32tool/openmv.py
stm32tool/entry/__init__.py
stm32tool/entry/dfu.py
stm32tool/entry/flash.py
stm32tool/entry/get_devices.py
stm32tool/entry/priview.py
stm32tool/entry/pydfu.py
stm32tool-0.0.10.dist-info/LICENSE
stm32tool-0.0.10.dist-info/METADATA
stm32tool-0.0.10.dist-info/WHEEL
stm32tool-0.0.10.dist-info/entry_points.txt
stm32tool-0.0.10.dist-info/top_level.txt
stm32tool-0.0.10.dist-info/RECORD
