Metadata-Version: 2.1
Name: stm32tool
Version: 0.0.10
Summary: Python stm32 tools
Home-page: https://github.com/kabirz/stm32tool
Author: Zhong huiping
Author-email: jxwazxzhp@126.com
License: MIT
Platform: linux
Classifier: Intended Audience :: Developers
Classifier: Operating System :: POSIX
Classifier: Programming Language :: Python :: 3.4
Classifier: Programming Language :: Python :: 3.5
Classifier: Programming Language :: Python :: 3.6
Classifier: Programming Language :: Python :: 3.7
Classifier: Topic :: Communications
Classifier: Topic :: Software Development :: Libraries
Classifier: Topic :: Software Development :: Libraries :: Python Modules
Requires-Dist: pyserial
Requires-Dist: Pillow
Requires-Dist: pygame
Requires-Dist: numpy
Requires-Dist: progressbar
